Metadata-Version: 1.0
Name: userapp.tornado
Version: 0.1.5dev
Summary: UserApp support for Tornado.
Home-page: https://github.com/userapp-io/userapp-tornado
Author: Robin Orheden
Author-email: robin.orheden@userapp.io
License: MIT
Keywords: tornado userapp
Platform: UNKNOWN
